geeutils/__init__.py
geeutils/eu.py
geeutils-2.0.0.dist-info/LICENSE
geeutils-2.0.0.dist-info/METADATA
geeutils-2.0.0.dist-info/WHEEL
geeutils-2.0.0.dist-info/top_level.txt
geeutils-2.0.0.dist-info/RECORD
