Metadata-Version: 2.1
Name: geeutils
Version: 2.0.0
Summary: Utility functions for Google Earth Engine
Home-page: https://github.com/CoralMapping/proc_gee_utils
Classifier: Programming Language :: Python :: 3
Classifier: License :: OSI Approved :: Apache Software License
Classifier: Operating System :: OS Independent
Requires-Python: >=3.10
License-File: LICENSE
Requires-Dist: earthengine-api (>=0.1.312)
